{
  "Sports": [
    {
      "sub": "Global Soccer",
      "n": 988
    },
    {
      "sub": "Tennis",
      "n": 529
    },
    {
      "sub": "Other Sports",
      "n": 362
    },
    {
      "sub": "eSports",
      "n": 182
    },
    {
      "sub": "NBA",
      "n": 169
    },
    {
      "sub": "MLB",
      "n": 91
    },
    {
      "sub": "F1 & Motorsport",
      "n": 57
    },
    {
      "sub": "NHL",
      "n": 26
    },
    {
      "sub": "Combat Sports",
      "n": 16
    },
    {
      "sub": "NFL",
      "n": 5
    },
    {
      "sub": "Olympics & Multi-sport",
      "n": 2
    }
  ],
  "World Politics": [
    {
      "sub": "Non-US Elections",
      "n": 529
    },
    {
      "sub": "International Relations & Conflicts",
      "n": 347
    }
  ],
  "Economy & Finance": [
    {
      "sub": "Financial Markets",
      "n": 603
    },
    {
      "sub": "Macroeconomics",
      "n": 123
    },
    {
      "sub": "Monetary Policy",
      "n": 76
    }
  ],
  "Crypto": [
    {
      "sub": "Speculation",
      "n": 628
    },
    {
      "sub": "Protocol & Launches",
      "n": 24
    },
    {
      "sub": "Price Predictions",
      "n": 8
    },
    {
      "sub": "Crypto Regulation",
      "n": 1
    }
  ],
  "US Politics": [
    {
      "sub": "Nominations & Primaries",
      "n": 263
    },
    {
      "sub": "Policy & Governance",
      "n": 158
    },
    {
      "sub": "Appointments",
      "n": 17
    },
    {
      "sub": "Presidential Elections",
      "n": 2
    }
  ],
  "Culture & Media": [
    {
      "sub": "Soundbites",
      "n": 270
    },
    {
      "sub": "Movies, TV & Awards",
      "n": 135
    },
    {
      "sub": "Celebrity & Events",
      "n": 86
    },
    {
      "sub": "Social Media",
      "n": 22
    }
  ],
  "AI & Tech": [
    {
      "sub": "Model Releases & Benchmarks",
      "n": 198
    },
    {
      "sub": "Tech Companies",
      "n": 50
    },
    {
      "sub": "Unclassified",
      "n": 3
    }
  ],
  "Miscellaneous": [
    {
      "sub": "Unclassified",
      "n": 14
    }
  ],
  "Science": [
    {
      "sub": "Weather & Disasters",
      "n": 77
    },
    {
      "sub": "Health & Science",
      "n": 22
    },
    {
      "sub": "Space",
      "n": 7
    }
  ]
}